potatomagical/__init__.py
potatomagical/magic.py
potatomagical-0.1.dist-info/METADATA
potatomagical-0.1.dist-info/WHEEL
potatomagical-0.1.dist-info/top_level.txt
potatomagical-0.1.dist-info/RECORD
