Metadata-Version: 2.1
Name: potatomagical
Version: 0.1
Summary: A simple magic package
Home-page: http://github.com/pkasinathan/potatomagical
Author: Prabhu Kasinathan
Author-email: vasuramprabhu@gmail.com
License: UNKNOWN
Platform: UNKNOWN
Classifier: License :: OSI Approved :: MIT License
Classifier: Programming Language :: Python
Classifier: Programming Language :: Python :: 3
Classifier: Programming Language :: Python :: 3.6
